ancient_scripts/__init__.py
ancient_scripts/core.py
ancient_scripts/mappings.py
scriptosantiquus-1.0.0.dist-info/METADATA
scriptosantiquus-1.0.0.dist-info/WHEEL
scriptosantiquus-1.0.0.dist-info/entry_points.txt
scriptosantiquus-1.0.0.dist-info/top_level.txt
scriptosantiquus-1.0.0.dist-info/RECORD
